zh2ru_idterms/__init__.py
zh2ru_idterms/api.py
zh2ru_idterms/db.py
zh2ru_idterms/schema.sql
zh2ru_idterms/data/terms.db
zh2ru_idterms-0.1.2.dist-info/METADATA
zh2ru_idterms-0.1.2.dist-info/WHEEL
zh2ru_idterms-0.1.2.dist-info/top_level.txt
zh2ru_idterms-0.1.2.dist-info/RECORD
