Metadata-Version: 2.4
Name: zh2ru-idterms
Version: 0.1.2
Summary: Chinese→Russian ID terms dictionary (places, authorities, surname/given-name rules) with a bundled SQLite DB.
Author: koko
License: MIT
Project-URL: Homepage, https://pypi.org/project/zh2ru-idterms/
Project-URL: Source, https://pypi.org/project/zh2ru-idterms/
Keywords: Chinese,Russian,Palladius,translation,passport,driving licence,SQLite,toponyms
Classifier: Programming Language :: Python :: 3
Classifier: Programming Language :: Python :: 3 :: Only
Classifier: License :: OSI Approved :: MIT License
Classifier: Operating System :: OS Independent
Classifier: Intended Audience :: Developers
Classifier: Topic :: Text Processing :: Linguistic
Classifier: Topic :: Software Development :: Libraries :: Python Modules
Requires-Python: >=3.8
